Metadata-Version: 1.1
Name: phlogo
Version: 0.6
Summary: Pornhub Logo Generator
Home-page: https://github.com/krypton-byte/drawHub
Author: Krypton Byte
Author-email: galaxyvplus6434@gmail.com
License: MIT
Download-URL: https://github.com/krypton-byte/drawHub/archive/0.0.1.tar.gz
Keywords: pornhub,logo,generator
Platform: UNKNOWN
Classifier: Development Status :: 3 - Alpha
Classifier: Intended Audience :: Developers
Classifier: Topic :: Software Development :: Build Tools
Classifier: License :: OSI Approved :: MIT License
Classifier: Programming Language :: Python :: 3.8
Classifier: Programming Language :: Python :: 3.9
